{
  "url": "https://api.github.com/repos/JuliaLang/julia/issues/60302",
  "repository_url": "https://api.github.com/repos/JuliaLang/julia",
  "labels_url": "https://api.github.com/repos/JuliaLang/julia/issues/60302/labels{/name}",
  "comments_url": "https://api.github.com/repos/JuliaLang/julia/issues/60302/comments",
  "events_url": "https://api.github.com/repos/JuliaLang/julia/issues/60302/events",
  "html_url": "https://github.com/JuliaLang/julia/pull/60302",
  "id": 3686883778,
  "node_id": "PR_kwDOABkWpM62qGn1",
  "number": 60302,
  "title": "cacert: Update to 2025-12-02",
  "user": {
    "login": "eschnett",
    "id": 213514,
    "node_id": "MDQ6VXNlcjIxMzUxNA==",
    "avatar_url": "https://avatars.githubusercontent.com/u/213514?v=4",
    "gravatar_id": "",
    "url": "https://api.github.com/users/eschnett",
    "html_url": "https://github.com/eschnett",
    "followers_url": "https://api.github.com/users/eschnett/followers",
    "following_url": "https://api.github.com/users/eschnett/following{/other_user}",
    "gists_url": "https://api.github.com/users/eschnett/gists{/gist_id}",
    "starred_url": "https://api.github.com/users/eschnett/starred{/owner}{/repo}",
    "subscriptions_url": "https://api.github.com/users/eschnett/subscriptions",
    "organizations_url": "https://api.github.com/users/eschnett/orgs",
    "repos_url": "https://api.github.com/users/eschnett/repos",
    "events_url": "https://api.github.com/users/eschnett/events{/privacy}",
    "received_events_url": "https://api.github.com/users/eschnett/received_events",
    "type": "User",
    "user_view_type": "public",
    "site_admin": false
  },
  "labels": [
    {
      "id": 210703,
      "node_id": "MDU6TGFiZWwyMTA3MDM=",
      "url": "https://api.github.com/repos/JuliaLang/julia/labels/building",
      "name": "building",
      "color": "444444",
      "default": false,
      "description": "Build system, or building Julia or its dependencies"
    },
    {
      "id": 550946078,
      "node_id": "MDU6TGFiZWw1NTA5NDYwNzg=",
      "url": "https://api.github.com/repos/JuliaLang/julia/labels/external%20dependencies",
      "name": "external dependencies",
      "color": "A87582",
      "default": false,
      "description": "Involves LLVM, OpenBLAS, or other linked libraries"
    },
    {
      "id": 2823814840,
      "node_id": "MDU6TGFiZWwyODIzODE0ODQw",
      "url": "https://api.github.com/repos/JuliaLang/julia/labels/JLLs",
      "name": "JLLs",
      "color": "3543B5",
      "default": false,
      "description": ""
    }
  ],
  "state": "closed",
  "locked": false,
  "assignee": {
    "login": "giordano",
    "id": 765740,
    "node_id": "MDQ6VXNlcjc2NTc0MA==",
    "avatar_url": "https://avatars.githubusercontent.com/u/765740?v=4",
    "gravatar_id": "",
    "url": "https://api.github.com/users/giordano",
    "html_url": "https://github.com/giordano",
    "followers_url": "https://api.github.com/users/giordano/followers",
    "following_url": "https://api.github.com/users/giordano/following{/other_user}",
    "gists_url": "https://api.github.com/users/giordano/gists{/gist_id}",
    "starred_url": "https://api.github.com/users/giordano/starred{/owner}{/repo}",
    "subscriptions_url": "https://api.github.com/users/giordano/subscriptions",
    "organizations_url": "https://api.github.com/users/giordano/orgs",
    "repos_url": "https://api.github.com/users/giordano/repos",
    "events_url": "https://api.github.com/users/giordano/events{/privacy}",
    "received_events_url": "https://api.github.com/users/giordano/received_events",
    "type": "User",
    "user_view_type": "public",
    "site_admin": false
  },
  "assignees": [
    {
      "login": "giordano",
      "id": 765740,
      "node_id": "MDQ6VXNlcjc2NTc0MA==",
      "avatar_url": "https://avatars.githubusercontent.com/u/765740?v=4",
      "gravatar_id": "",
      "url": "https://api.github.com/users/giordano",
      "html_url": "https://github.com/giordano",
      "followers_url": "https://api.github.com/users/giordano/followers",
      "following_url": "https://api.github.com/users/giordano/following{/other_user}",
      "gists_url": "https://api.github.com/users/giordano/gists{/gist_id}",
      "starred_url": "https://api.github.com/users/giordano/starred{/owner}{/repo}",
      "subscriptions_url": "https://api.github.com/users/giordano/subscriptions",
      "organizations_url": "https://api.github.com/users/giordano/orgs",
      "repos_url": "https://api.github.com/users/giordano/repos",
      "events_url": "https://api.github.com/users/giordano/events{/privacy}",
      "received_events_url": "https://api.github.com/users/giordano/received_events",
      "type": "User",
      "user_view_type": "public",
      "site_admin": false
    }
  ],
  "milestone": null,
  "comments": 0,
  "created_at": "2025-12-02T17:37:57Z",
  "updated_at": "2026-01-09T13:31:55Z",
  "closed_at": "2025-12-02T21:40:29Z",
  "author_association": "CONTRIBUTOR",
  "type": null,
  "active_lock_reason": null,
  "draft": false,
  "pull_request": {
    "url": "https://api.github.com/repos/JuliaLang/julia/pulls/60302",
    "html_url": "https://github.com/JuliaLang/julia/pull/60302",
    "diff_url": "https://github.com/JuliaLang/julia/pull/60302.diff",
    "patch_url": "https://github.com/JuliaLang/julia/pull/60302.patch",
    "merged_at": "2025-12-02T21:40:29Z"
  },
  "body": null,
  "reactions": {
    "url": "https://api.github.com/repos/JuliaLang/julia/issues/60302/reactions",
    "total_count": 0,
    "+1": 0,
    "-1": 0,
    "laugh": 0,
    "hooray": 0,
    "confused": 0,
    "heart": 0,
    "rocket": 0,
    "eyes": 0
  },
  "timeline_url": "https://api.github.com/repos/JuliaLang/julia/issues/60302/timeline",
  "performed_via_github_app": null,
  "state_reason": null,
  "score": 1.0,
  "files": [
    {
      "sha": "641a98aecef0284bb8fabe0a6e0d7be4ac07df0b",
      "filename": "deps/checksums/cacert-2025-11-04.pem/md5",
      "status": "removed",
      "additions": 0,
      "deletions": 1,
      "changes": 1,
      "blob_url": "https://github.com/JuliaLang/julia/blob/af36919d1c3d0e5b54525ee1e6433c892c58a07a/deps%2Fchecksums%2Fcacert-2025-11-04.pem%2Fmd5",
      "raw_url": "https://github.com/JuliaLang/julia/raw/af36919d1c3d0e5b54525ee1e6433c892c58a07a/deps%2Fchecksums%2Fcacert-2025-11-04.pem%2Fmd5",
      "contents_url": "https://api.github.com/repos/JuliaLang/julia/contents/deps%2Fchecksums%2Fcacert-2025-11-04.pem%2Fmd5?ref=af36919d1c3d0e5b54525ee1e6433c892c58a07a",
      "patch": "@@ -1 +0,0 @@\n-4ca8e1c3e8fc44c3ecd7a1fb9d3a6d03"
    },
    {
      "sha": "bbd48b9475d7fe73a39652c41e839728213e0bb9",
      "filename": "deps/checksums/cacert-2025-11-04.pem/sha512",
      "status": "removed",
      "additions": 0,
      "deletions": 1,
      "changes": 1,
      "blob_url": "https://github.com/JuliaLang/julia/blob/af36919d1c3d0e5b54525ee1e6433c892c58a07a/deps%2Fchecksums%2Fcacert-2025-11-04.pem%2Fsha512",
      "raw_url": "https://github.com/JuliaLang/julia/raw/af36919d1c3d0e5b54525ee1e6433c892c58a07a/deps%2Fchecksums%2Fcacert-2025-11-04.pem%2Fsha512",
      "contents_url": "https://api.github.com/repos/JuliaLang/julia/contents/deps%2Fchecksums%2Fcacert-2025-11-04.pem%2Fsha512?ref=af36919d1c3d0e5b54525ee1e6433c892c58a07a",
      "patch": "@@ -1 +0,0 @@\n-9d9f7ecc829bafc222501d8a66852d96a51f522b04a82963e4166c87b85d6a5e5eedb50ced2ef3026cd7cb06fcb4b7dca59c4157813a067cb7b185e32f2957ec"
    },
    {
      "sha": "c482d2cc8dc9c11f8547f4baceae29539114f5c6",
      "filename": "deps/checksums/cacert-2025-12-02.pem/md5",
      "status": "added",
      "additions": 1,
      "deletions": 0,
      "changes": 1,
      "blob_url": "https://github.com/JuliaLang/julia/blob/c37e724e2a8ca15854ceedd83013da744aca77bd/deps%2Fchecksums%2Fcacert-2025-12-02.pem%2Fmd5",
      "raw_url": "https://github.com/JuliaLang/julia/raw/c37e724e2a8ca15854ceedd83013da744aca77bd/deps%2Fchecksums%2Fcacert-2025-12-02.pem%2Fmd5",
      "contents_url": "https://api.github.com/repos/JuliaLang/julia/contents/deps%2Fchecksums%2Fcacert-2025-12-02.pem%2Fmd5?ref=c37e724e2a8ca15854ceedd83013da744aca77bd",
      "patch": "@@ -0,0 +1 @@\n+fafa2b78f98273ea332251e3d1628b02"
    },
    {
      "sha": "92e9d653aee45f4ded174257b68ec20da8ad8165",
      "filename": "deps/checksums/cacert-2025-12-02.pem/sha512",
      "status": "added",
      "additions": 1,
      "deletions": 0,
      "changes": 1,
      "blob_url": "https://github.com/JuliaLang/julia/blob/c37e724e2a8ca15854ceedd83013da744aca77bd/deps%2Fchecksums%2Fcacert-2025-12-02.pem%2Fsha512",
      "raw_url": "https://github.com/JuliaLang/julia/raw/c37e724e2a8ca15854ceedd83013da744aca77bd/deps%2Fchecksums%2Fcacert-2025-12-02.pem%2Fsha512",
      "contents_url": "https://api.github.com/repos/JuliaLang/julia/contents/deps%2Fchecksums%2Fcacert-2025-12-02.pem%2Fsha512?ref=c37e724e2a8ca15854ceedd83013da744aca77bd",
      "patch": "@@ -0,0 +1 @@\n+aef293e084ef15a55a4f9dee395ee4bbbadea1f5a49c0590e0ff67a0630b5298d2bc79699ab95d70be0d2d06f9f1e55fe676b3e1d5ff912df88f2d6bff0d5736"
    },
    {
      "sha": "a39088064168ff86a46aba0ced31191e39cc6e54",
      "filename": "deps/libgit2.version",
      "status": "modified",
      "additions": 1,
      "deletions": 1,
      "changes": 2,
      "blob_url": "https://github.com/JuliaLang/julia/blob/c37e724e2a8ca15854ceedd83013da744aca77bd/deps%2Flibgit2.version",
      "raw_url": "https://github.com/JuliaLang/julia/raw/c37e724e2a8ca15854ceedd83013da744aca77bd/deps%2Flibgit2.version",
      "contents_url": "https://api.github.com/repos/JuliaLang/julia/contents/deps%2Flibgit2.version?ref=c37e724e2a8ca15854ceedd83013da744aca77bd",
      "patch": "@@ -11,4 +11,4 @@ LIBGIT2_SHA1=0060d9cf5666f015b1067129bd874c6cc4c9c7ac\n # The versions of cacert.pem are identified by the date (YYYY-MM-DD) of their changes.\n # See https://curl.haxx.se/docs/caextract.html for more details.\n # Keep in sync with `stdlib/MozillaCACerts_jll/Project.toml`.\n-MOZILLA_CACERT_VERSION := 2025-11-04\n+MOZILLA_CACERT_VERSION := 2025-12-02"
    },
    {
      "sha": "d33a5c9252d5094eef8d88abef0d7a5b53ad2003",
      "filename": "stdlib/MozillaCACerts_jll/Project.toml",
      "status": "modified",
      "additions": 1,
      "deletions": 1,
      "changes": 2,
      "blob_url": "https://github.com/JuliaLang/julia/blob/c37e724e2a8ca15854ceedd83013da744aca77bd/stdlib%2FMozillaCACerts_jll%2FProject.toml",
      "raw_url": "https://github.com/JuliaLang/julia/raw/c37e724e2a8ca15854ceedd83013da744aca77bd/stdlib%2FMozillaCACerts_jll%2FProject.toml",
      "contents_url": "https://api.github.com/repos/JuliaLang/julia/contents/stdlib%2FMozillaCACerts_jll%2FProject.toml?ref=c37e724e2a8ca15854ceedd83013da744aca77bd",
      "patch": "@@ -1,7 +1,7 @@\n name = \"MozillaCACerts_jll\"\n uuid = \"14a3606d-f60d-562e-9121-12d972cd8159\"\n # Keep in sync with `deps/libgit2.version`.\n-version = \"2025.11.04\"\n+version = \"2025.12.02\"\n \n [extras]\n Test = \"8dfed614-e22c-5e08-85e1-65c5234f0b40\""
    }
  ]
}